flask_softdelete/__init__.py
flask_softdelete/softdelete.py
flask_softdelete-2.1.0.dist-info/LICENCE
flask_softdelete-2.1.0.dist-info/METADATA
flask_softdelete-2.1.0.dist-info/WHEEL
flask_softdelete-2.1.0.dist-info/top_level.txt
flask_softdelete-2.1.0.dist-info/RECORD
