Metadata-Version: 2.1
Name: flask-softdelete
Version: 2.1.0
Summary: A simple mixin for adding soft delete functionality to Flask-SQLAlchemy models
Home-page: https://github.com/Moesthetics-code/flask-softdelete
Author: Mohamed Ndiaye
Author-email: mintok2000@gmail.com
Classifier: Programming Language :: Python :: 3
Classifier: Framework :: Flask
Classifier: License :: OSI Approved :: MIT License
Classifier: Operating System :: OS Independent
Requires-Python: >=3.6
License-File: LICENCE
Requires-Dist: Flask>=2.0.0
Requires-Dist: Flask-SQLAlchemy>=2.5.0
